Module/Math_module.py
Module/__init__.py
mathmodule13547-0.1.0.dist-info/METADATA
mathmodule13547-0.1.0.dist-info/WHEEL
mathmodule13547-0.1.0.dist-info/top_level.txt
mathmodule13547-0.1.0.dist-info/RECORD
